rtl/imm_gen.v
`timescale 1ps/1ps
`default_nettype none
`include "rtl/isa.v"

module imm_gen (
    input wire [`XLEN-1:0] instruction,
    output reg [`XLEN-1:0] immediate
);
    
    wire [6:0] opcode;
    assign opcode = instruction[6:0];

    wire [`XLEN-1:0] i_imm = {{20{instruction[31]}}, instruction[31:20]};
    wire [`XLEN-1:0] s_imm = {{20{instruction[31]}}, instruction[31:25], instruction[11:7]};
    wire [`XLEN-1:0] b_imm = {{19{instruction[31]}}, instruction[31], instruction[7], instruction[30:25], instruction[11:8], 1'b0};
    wire [`XLEN-1:0] u_imm = {instruction[31:12], 12'b0};
    wire [`XLEN-1:0] j_imm = {{11{instruction[31]}}, instruction[31], instruction[19:12], instruction[20], instruction[30:21], 1'b0};

    always @(*) begin
        case (opcode)
            `OP_IMM, `OP_IMM_LOAD, `OP_J_JALR: immediate = i_imm;
            // `OP_IMM, `OP_IMM_LOAD: immediate = i_imm;
            `OP_S_TYPE: immediate = s_imm;
            `OP_B_TYPE: immediate = b_imm;
            `OP_U_LUI, `OP_U_AUIPC: immediate = u_imm;
            `OP_J_JAL: immediate = j_imm;
            default: immediate = {`XLEN{1'b0}};
        endcase
    end
    
endmodule

tb/tb_imm_gen.sv
import riscv_pkg::*;

module tb_imm_gen;
    timeunit 1ns;
    timeprecision 1ps;
    
    logic [XLEN-1:0] immediate;
    logic [XLEN-1:0] instruction;

    int pass_count = 0;
    int fail_count = 0;
    
    imm_gen dut (
        .instruction(instruction),
        .immediate(immediate)
    );

    task automatic check_imm(
        input logic [XLEN-1:0] expected
    );
        #1;
        if (immediate == expected) begin
            $display("PASS: expected: %h, got: %h",expected, immediate);
            pass_count++;
        end else begin
            $error("FAIL: expected: %h, got: %h", expected, immediate);
            fail_count++;
        end
    endtask

    function automatic logic [XLEN-1:0] build_instruction(
        input logic [6:0] opcode,
        input logic [4:0] rd,
        input logic [2:0] funct3,
        input logic [2:0] rs1,
        input logic [4:0] rs2,
        input logic [6:0] funct7
    );
        return {funct7, rs2, rs1, funct3, rd, opcode};

    endfunction

    initial begin
        $dumpfile("imm_gen.vcd");
        $dumpvars(0, tb_imm_gen);

        $display("Imm gen tb\n");

        $display("\nI type");
        // positive immediate
        instruction = {12'h123, 5'd1, 3'b000, 5'd2, OP_IMM};
        check_imm(32'h00000123);
        
        // negative immediate
        instruction = {12'hFF, 5'd1, 3'b000, 5'd2, OP_IMM};
        check_imm(32'hFFFFFFFF);

        // zero immediate
        instruction = {12'h000, 5'd1, 3'b000, 5'd2, OP_IMM};
        check_imm(32'h00000000);

        // max positive
        instruction = {12'hFF, 5'd1, 3'b000, 5'd2, OP_LOAD};
        check_imm(32'h000007FF);

        // min negative
        instruction = {12'h800, 5'd1, 3'b000, 5'd2, OP_JALR};
        check_imm(32'hFFFFF800);

        // S-TYPE
        $display("\nS type");

        // positive immediate
        instruction = {7'h09, 5'd2, 5'd1, 3'b010, 5'h0A, OP_STORE};
        check_imm(32'h0000012A);

        // negative immediate
        instruction = {7'hF, 5'd2, 5'd1, 3'b010, 5'h1F, OP_STORE};
        check_imm(32'hFFFFFFFF);

        // zero
        instruction = {7'h00, 5'd2, 5'd1, 3'b010, 5'h00, OP_STORE};
        check_imm(32'h00000000);

        $display("\nB type");
        
        // psotive brach offset (forwadrd)
        instruction = {1'b0, 6'b0, 5'd2, 5'd1, 3'b000, 4'b0100, 1'b0, OP_BRANCH};
        check_imm(32'h00000008);

        // negative branch offset (backward)
        instruction = {1'b1, 6'b1, 5'd2, 5'd1, 3'b000, 4'b1, 1'b1, OP_BRANCH};
        check_imm(32'hFFFFFFFE);

        // zero offset
        instruction = {1'b0, 6'b0, 5'd2, 5'd1, 3'b0, 4'b0, 1'b0, OP_BRANCH};
        check_imm(32'h00000000);

        $display("\nU type");
        
        // lui upper
        instruction = {20'h12345, 5'd1, OP_LUI};
        check_imm(32'h12345000);

        // AUIPC upperr
        instruction = {20'hFFFFF, 5'd1, OP_AUIPC};
        check_imm(32'hFFFFF000);

        // zero
        instruction = {20'h00000, 5'd1, OP_LUI};
        check_imm(32'h00000000);

        $display("\nJ type");
        // positive jump offset
        instruction = {1'b0, 10'b0000000010, 1'b0, 8'b0, 5'd1, OP_JAL};
        check_imm(32'h00000004);

        // zero
        instruction = {1'b0, 10'b0, 1'b0, 8'b0, 5'd1, OP_JAL};
        check_imm(32'h00000000);

        // larger positive offest
        instruction = {1'b0, 10'b0000010000, 1'b0, 8'b0, 5'd1, OP_JAL};
        check_imm(32'h00000020);

        $display("Edge cases");
        instruction = 32'hFFFFFFFF;
        instruction[6:0] = 7'b1111111;
        check_imm(32'h00000000);

        // Resutls
        #10;
        $display("\nTest summary");
        $display("passd: %0d", pass_count);
        $display("failed: %0d", fail_count);
        $display("total: %0d", pass_count + fail_count);
        if (fail_count == 0)
            $display("all test passed");
        else
            $display("some test failed");

        $finish;
    end


    initial begin
        #10000;
        $error("TIMEOUT: Tb did not compile in time");
        $finish;
    end

endmodule

imm_gen.vcd
$date
   Wed Jan  7 18:04:24 2026
$end

$version
  2025.1.0
  $dumpfile ("imm_gen.vcd") 
$end

$timescale
  1ps
$end

$scope module tb_imm_gen $end
$var reg 32 ! immediate [31:0] $end
$var reg 32 " instruction [31:0] $end
$var reg 32 # pass_count [31:0] $end
$var reg 32 $ fail_count [31:0] $end
$scope module dut $end
$var wire 32 % instruction [31:0] $end
$var reg 32 ! immediate [31:0] $end
$var reg 7 & opcode [6:0] $end
$var reg 32 ' i_imm [31:0] $end
$var reg 32 ( s_imm [31:0] $end
$var reg 32 ) b_imm [31:0] $end
$var reg 32 * u_imm [31:0] $end
$var reg 32 + j_imm [31:0] $end
$upscope $end
$scope task check_imm $end
$upscope $end
$upscope $end
$enddefinitions $end

#0
$dumpvars
b100100011 !
b10010001100001000000100010011 "
b0 #
b0 $
b10010001100001000000100010011 %
b10011 &
b100100011 '
b100100010 (
b100100010 )
b10010001100001000000000000000 *
b1000100100100010 +
$end

#1000
b11111111 !
b1111111100001000000100010011 "
b1 #
b1111111100001000000100010011 %
b11111111 '
b11100010 (
b11100010 )
b1111111100001000000000000000 *
b1000100011111110 +

#2000
b0 !
b1000000100010011 "
b1 $
b1000000100010011 %
b0 '
b10 (
b10 )
b1000000000000000 *
b1000000000000000 +

#3000
b11111111 !
b1111111100001000000100000011 "
b10 #
b1111111100001000000100000011 %
b11 &
b11111111 '
b11100010 (
b11100010 )
b1111111100001000000000000000 *
b1000100011111110 +

#4000
b11111111111111111111100000000000 !
b10000000000000001000000101100111 "
b10 $
b10000000000000001000000101100111 %
b1100111 &
b11111111111111111111100000000000 '
b11111111111111111111100000000010 (
b11111111111111111111000000000010 )
b10000000000000001000000000000000 *
b11111111111100001000000000000000 +

#5000
b100101010 !
b10010001000001010010100100011 "
b11 #
b10010001000001010010100100011 %
b100011 &
b100100010 '
b100101010 (
b100101010 )
b10010001000001010000000000000 *
b1010000100100010 +

#6000
b111111111 !
b11110001000001010111110100011 "
b100 #
b11110001000001010111110100011 %
b111100010 '
b111111111 (
b100111111110 )
b11110001000001010000000000000 *
b1010000111100010 +

#7000
b0 !
b1000001010000000100011 "
b11 $
b1000001010000000100011 %
b10 '
b0 (
b0 )
b1000001010000000000000 *
b1010000000000010 +

#8000
b1000 !
b1000001000010001100011 "
b101 #
b1000001000010001100011 %
b1100011 &
b1000 (
b1000 )
b1000001000000000000000 *
b1000000000000010 +

#9000
b11111111111111111111100000100010 !
b10000010001000001000000111100011 "
b110 #
b10000010001000001000000111100011 %
b11111111111111111111100000100010 '
b11111111111111111111100000100011 (
b11111111111111111111100000100010 )
b10000010001000001000000000000000 *
b11111111111100001000000000100010 +

#10000
b0 !
b1000001000000001100011 "
b100 $
b1000001000000001100011 %
b10 '
b0 (
b0 )
b1000001000000000000000 *
b1000000000000010 +

#11000
b10010001101000101000000000000 !
b10010001101000101000010110111 "
b111 #
b10010001101000101000010110111 %
b110111 &
b100100011 '
b100100001 (
b100100100000 )
b10010001101000101000000000000 *
b1000101100100100010 +

#12000
b11111111111111111111000000000000 !
b11111111111111111111000010010111 "
b1000 #
b11111111111111111111000010010111 %
b10111 &
b11111111111111111111111111111111 '
b11111111111111111111111111100001 (
b11111111111111111111111111100000 )
b11111111111111111111000000000000 *
b11111111111111111111111111111110 +

#13000
b0 !
b10110111 "
b1001 #
b10110111 %
b110111 &
b0 '
b1 (
b100000000000 )
b0 *
b0 +

#14000
b100 !
b10000000000000011101111 "
b1010 #
b10000000000000011101111 %
b1101111 &
b100 '
b10000000000000000000000 *
b100 +

#15000
b0 !
b11101111 "
b1011 #
b11101111 %
b0 '
b0 *
b0 +

#16000
b100000 !
b10000000000000000011101111 "
b1100 #
b10000000000000000011101111 %
b100000 '
b100001 (
b100000100000 )
b10000000000000000000000000 *
b100000 +

#17000
b0 !
b11111111111111111111111111111111 "
b1101 #
b11111111111111111111111111111111 %
b1111111 &
b11111111111111111111111111111111 '
b11111111111111111111111111111111 (
b11111111111111111111111111111110 )
b11111111111111111111000000000000 *
b11111111111111111111111111111110 +

#18000
b1110 #
